kicksaw_aws_iam_policy_management/__init__.py
kicksaw_aws_iam_policy_management/cli.py
kicksaw_aws_iam_policy_management/dupe.py
kicksaw_aws_iam_policy_management/script.py
kicksaw_aws_iam_policy_management-0.1.0.dist-info/entry_points.txt
kicksaw_aws_iam_policy_management-0.1.0.dist-info/WHEEL
kicksaw_aws_iam_policy_management-0.1.0.dist-info/METADATA
kicksaw_aws_iam_policy_management-0.1.0.dist-info/RECORD
